pravda/__init__.py
pravda/example.py
pravda/py.typed
pravda-0.0.0.dist-info/LICENSE
pravda-0.0.0.dist-info/WHEEL
pravda-0.0.0.dist-info/METADATA
pravda-0.0.0.dist-info/RECORD
